compact_json/__init__.py
compact_json/__main__.py
compact_json/_compact_json.py
compact_json/formatter.py
compact_json-1.8.2.dist-info/METADATA
compact_json-1.8.2.dist-info/WHEEL
compact_json-1.8.2.dist-info/entry_points.txt
compact_json-1.8.2.dist-info/licenses/LICENSE.rst
compact_json-1.8.2.dist-info/RECORD
