Metadata-Version: 2.4
Name: compact-json
Version: 1.8.2
Summary: A JSON formatter that produces compact but human-readable
License: MIT
License-File: LICENSE.rst
Author: Jon Connell
Author-email: python@figsandfudge.com
Requires-Python: >=3.9,<4.0
Classifier: License :: OSI Approved :: MIT License
Classifier: Operating System :: OS Independent
Classifier: Programming Language :: Python :: 3
Classifier: Programming Language :: Python :: 3.9
Classifier: Programming Language :: Python :: 3.10
Classifier: Programming Language :: Python :: 3.11
Classifier: Programming Language :: Python :: 3.12
Classifier: Programming Language :: Python :: 3.13
Classifier: Programming Language :: Python :: 3.14
Requires-Dist: importlib-resources (>=6.1)
Requires-Dist: setuptools (>=69.0.3)
Requires-Dist: wcwidth (>0.2.8)
Project-URL: Documentation, https://github.com/masaccio/compact-json/blob/main/README.md
Project-URL: Repository, https://github.com/masaccio/compact-json
